log5/__init__.py
log5-1.0.1.dist-info/licenses/LICENSE
log5-1.0.1.dist-info/METADATA
log5-1.0.1.dist-info/WHEEL
log5-1.0.1.dist-info/top_level.txt
log5-1.0.1.dist-info/RECORD
