Metadata-Version: 2.4
Name: log5
Version: 1.0.1
Summary: Output logs
Home-page: https://github.com/hailiang-wang/python-log5
Author: Hai Liang Wang
Author-email: hailiang.hl.wang@gmail.com
License: Chunsong Public License, version 1.0
Keywords: logging
Classifier: Intended Audience :: Developers
Classifier: Operating System :: OS Independent
Classifier: Natural Language :: Chinese (Simplified)
Classifier: Natural Language :: Chinese (Traditional)
Classifier: Programming Language :: Python
Classifier: Programming Language :: Python :: 3
Classifier: Programming Language :: Python :: 3.11
License-File: LICENSE
Dynamic: author
Dynamic: author-email
Dynamic: classifier
Dynamic: description
Dynamic: home-page
Dynamic: keywords
Dynamic: license
Dynamic: license-file
Dynamic: summary
